opta_read/__init__.py
opta_read/f1_function.py
opta_read/f27_function.py
opta_read/f28_function.py
opta_read/f30_function.py
opta_read/f71_function.py
opta_read/_auxiliares/__init__.py
opta_read/_auxiliares/f1_aux_funct.py
opta_read/_auxiliares/f27_aux_funct.py
opta_read/_auxiliares/f28_aux_funct.py
opta_read/_auxiliares/f30_aux_funct.py
opta_read/_auxiliares/f71_aux_funct.py
opta_read/_auxiliares/opta_pitch.py
opta_read-0.0.2.dist-info/METADATA
opta_read-0.0.2.dist-info/WHEEL
opta_read-0.0.2.dist-info/top_level.txt
opta_read-0.0.2.dist-info/RECORD
