Metadata-Version: 2.1
Name: opta-read
Version: 0.0.2
Summary: Librería para leer ficheros de xml de Opta y extraer la información
Home-page: https://github.com/felsuacor/BD_deporte
Author: Felix Suarez
License: MIT
Platform: UNKNOWN
Requires-Dist: pandas
Requires-Dist: numpy
Requires-Dist: more-itertools
Requires-Dist: matplotlib
Requires-Dist: seaborn
Requires-Dist: typing-extensions
Requires-Dist: networkx
Requires-Dist: scikit-learn
Requires-Dist: plotly
